main.py
snudlhelper-0.0.1.dist-info/LICENSE
snudlhelper-0.0.1.dist-info/METADATA
snudlhelper-0.0.1.dist-info/WHEEL
snudlhelper-0.0.1.dist-info/top_level.txt
snudlhelper-0.0.1.dist-info/RECORD
